GodEatsPython/__init__.py
GodEatsPython/engine.py
GodEatsPython-0.0.2.dist-info/LICENSE
GodEatsPython-0.0.2.dist-info/METADATA
GodEatsPython-0.0.2.dist-info/WHEEL
GodEatsPython-0.0.2.dist-info/top_level.txt
GodEatsPython-0.0.2.dist-info/RECORD
