Metadata-Version: 2.1
Name: GodEatsPython
Version: 0.0.2
Summary: God Eats Python. A fully functioning simulation library.
Author-email: ApplePieCodes <ApplePiePc@outlook.com>
Project-URL: Homepage, https://github.com/ApplePieCodes/GodEatsPython
Project-URL: Issues, https://github.com/ApplePieCodes/GodEatsPython/issues
Classifier: Programming Language :: Python :: 3
Classifier: License :: OSI Approved :: MIT License
Classifier: Operating System :: OS Independent
Requires-Python: >=3.10
License-File: LICENSE
